realtime_redis_backup/__init__.py
realtime_redis_backup/__main__.py
realtime_redis_backup/__main__restore__.py
realtime_redis_backup/binary_format.py
realtime_redis_backup/rrb.py
realtime_redis_backup/shared.py
realtime_redis_backup-0.0.1.dist-info/LICENSE
realtime_redis_backup-0.0.1.dist-info/METADATA
realtime_redis_backup-0.0.1.dist-info/WHEEL
realtime_redis_backup-0.0.1.dist-info/entry_points.txt
realtime_redis_backup-0.0.1.dist-info/top_level.txt
realtime_redis_backup-0.0.1.dist-info/zip-safe
realtime_redis_backup-0.0.1.dist-info/RECORD
